{
  "id": "",
  "name": "",
  "font_family": "iconfont",
  "css_prefix_text": "icon-",
  "description": "",
  "glyphs": [
    {
      "icon_id": "145699",
      "name": "电话_填充",
      "font_class": "dianhuatianchong",
      "unicode": "e678",
      "unicode_decimal": 59000
    },
    {
      "icon_id": "431778",
      "name": "git",
      "font_class": "git",
      "unicode": "e708",
      "unicode_decimal": 59144
    },
    {
      "icon_id": "577389",
      "name": "坐标-fill",
      "font_class": "zuobiaofill",
      "unicode": "e768",
      "unicode_decimal": 59240
    },
    {
      "icon_id": "1330577",
      "name": "QQ",
      "font_class": "QQ",
      "unicode": "e73e",
      "unicode_decimal": 59198
    },
    {
      "icon_id": "3483765",
      "name": "邮箱",
      "font_class": "youxiang",
      "unicode": "e672",
      "unicode_decimal": 58994
    },
    {
      "icon_id": "6496026",
      "name": "Vue",
      "font_class": "Vue",
      "unicode": "e799",
      "unicode_decimal": 59289
    },
    {
      "icon_id": "7516912",
      "name": "学历",
      "font_class": "xueli",
      "unicode": "e611",
      "unicode_decimal": 58897
    },
    {
      "icon_id": "10584851",
      "name": "年龄",
      "font_class": "nianling",
      "unicode": "e69d",
      "unicode_decimal": 59037
    },
    {
      "icon_id": "12600657",
      "name": "css",
      "font_class": "css",
      "unicode": "e61e",
      "unicode_decimal": 58910
    },
    {
      "icon_id": "12600727",
      "name": "html",
      "font_class": "html",
      "unicode": "e632",
      "unicode_decimal": 58930
    },
    {
      "icon_id": "12600760",
      "name": "js",
      "font_class": "js",
      "unicode": "e63b",
      "unicode_decimal": 58939
    },
    {
      "icon_id": "13304144",
      "name": "vscode",
      "font_class": "vscode",
      "unicode": "e6b8",
      "unicode_decimal": 59064
    },
    {
      "icon_id": "13304147",
      "name": "vuex-store",
      "font_class": "vuex-store",
      "unicode": "e6bb",
      "unicode_decimal": 59067
    },
    {
      "icon_id": "15378331",
      "name": "eslint",
      "font_class": "eslint",
      "unicode": "eb8a",
      "unicode_decimal": 60298
    },
    {
      "icon_id": "15933094",
      "name": "微信",
      "font_class": "weixin",
      "unicode": "e607",
      "unicode_decimal": 58887
    },
    {
      "icon_id": "25672383",
      "name": "饿了么",
      "font_class": "elemo",
      "unicode": "fee2",
      "unicode_decimal": 65250
    }
  ]
}
